fs_helper/__init__.py
fs_helper-0.0.12.dist-info/LICENSE.txt
fs_helper-0.0.12.dist-info/METADATA
fs_helper-0.0.12.dist-info/WHEEL
fs_helper-0.0.12.dist-info/top_level.txt
fs_helper-0.0.12.dist-info/RECORD
