Metadata-Version: 2.1
Name: fs-helper
Version: 0.0.12
Summary: CLI helpers for filesystem and logging tasks
Home-page: https://github.com/kenjyco/fs-helper
Download-URL: https://github.com/kenjyco/fs-helper/tarball/v0.0.12
Author: Ken
Author-email: kenjyco@gmail.com
License: MIT
Keywords: filesystem,logging,files,helper,kenjyco
Platform: UNKNOWN
Classifier: Development Status :: 4 - Beta
Classifier: Environment :: Console
Classifier: Intended Audience :: Developers
Classifier: License :: OSI Approved :: MIT License
Classifier: Operating System :: MacOS :: MacOS X
Classifier: Operating System :: POSIX :: Linux
Classifier: Programming Language :: Python :: 3.5
Classifier: Programming Language :: Python :: 3.6
Classifier: Programming Language :: Python :: 3.7
Classifier: Programming Language :: Python :: 3.8
Classifier: Programming Language :: Python :: 3.9
Classifier: Programming Language :: Python :: 3.10
Classifier: Programming Language :: Python :: 3.11
Classifier: Programming Language :: Python :: 3.12
Classifier: Programming Language :: Python :: 3.13
Classifier: Programming Language :: Python
Classifier: Topic :: Software Development :: Libraries
Classifier: Topic :: System :: Filesystems
Classifier: Topic :: System :: Logging
Classifier: Topic :: Utilities
License-File: LICENSE.txt
